UI_Test_Project/__init__.py
UI_Test_Project/conftest.py
UI_Test_Project/common/__init__.py
UI_Test_Project/common/browser.py
UI_Test_Project/common/data_provide.py
UI_Test_Project/common/find_element_until.py
UI_Test_Project/common/parse_excel.py
UI_Test_Project/common/report.py
UI_Test_Project/config/__init__.py
UI_Test_Project/config/url_config.py
UI_Test_Project/fixture/__init__.py
UI_Test_Project/fixture/baidu_fixture.py
UI_Test_Project/lib/HTMLTestRunner.py
UI_Test_Project/lib/__init__.py
UI_Test_Project/main/__init__.py
UI_Test_Project/main/run_test_allure.py
UI_Test_Project/main/run_test_by_name.py
UI_Test_Project/main/run_test_by_tag.py
UI_Test_Project/main/run_test_general_html.py
UI_Test_Project/pages/__init__.py
UI_Test_Project/pages/baidu_home_page.py
UI_Test_Project/pages/baidu_news_page.py
UI_Test_Project/pages/baidu_search_page.py
UI_Test_Project/report/__init__.py
UI_Test_Project/test_case/__init__.py
UI_Test_Project/test_case/test_01_baidu_home_page.py
UI_Test_Project/test_case/test_02_baidu_home_page.py
UI_Test_Project/test_case/test_02_baidu_news_page.py
UI_Test_Project/test_case/test_02_baidu_search_flow.py
UI_Test_Project/test_case/test_03_baidu_home_page.py
UI_Test_Project/test_case/test_03_baidu_news_page.py
UI_Test_Project/test_case/test_04_baidu_search_flow.py
UI_Test_Project/test_case/test_05_baidu_home_page.py
UI_Test_Project/test_case/test_05_baidu_news_page.py
UI_Test_Project/test_data/__init__.py
UI_Test_Project-1.0.2.dist-info/LICENSE
UI_Test_Project-1.0.2.dist-info/METADATA
UI_Test_Project-1.0.2.dist-info/WHEEL
UI_Test_Project-1.0.2.dist-info/top_level.txt
UI_Test_Project-1.0.2.dist-info/RECORD
